minmon/__init__.py
minmon/__main__.py
minmon-0.9.9.dist-info/entry_points.txt
minmon-0.9.9.dist-info/WHEEL
minmon-0.9.9.dist-info/METADATA
minmon-0.9.9.dist-info/RECORD
