Metadata-Version: 2.1
Name: minmon
Version: 0.9.9
Summary: MINimal MONitor - write and graph: date, time, memory, CPU, temperature, disk i/o and net i/o
Author-email: Carlo Alessandro Verre <carlo.alessandro.verre@gmail.com>
Requires-Python: >=3.6
Classifier: Programming Language :: Python :: 3
Classifier: Programming Language :: Python :: 3.6
Classifier: Development Status :: 4 - Beta
Classifier: Environment :: Console
Classifier: Intended Audience :: Developers
Classifier: Intended Audience :: End Users/Desktop
Classifier: License :: OSI Approved :: GNU General Public License v3 or later (GPLv3+)
Classifier: Operating System :: POSIX :: Linux
Requires-Dist: psutil
Project-URL: Home, https://pypi.org/project/minmon
